{
  "_fv": 66,
  "_type": "achievement",
  "definition": {
    "achievementName": "Domino",
    "achievementDescription": "Everything usually works out for me.",
    "achievementIcon": {
      "value": "CUSTOM:DominoIcon"
    },
    "background": "Default",
    "disableDisplay": false,
    "showPopup": true,
    "announceToChat": true,
    "hideIfNotCompleted": true,
    "rewardLoot": [],
    "rewardRecipes": [],
    "rewardFunction": "No function",
    "rewardXP": 3,
    "achievementType": "task",
    "parent": {
      "value": "CUSTOM:XGene"
    },
    "triggerxml": "<?xml version=\"1.0\" encoding=\"UTF-8\" standalone=\"no\"?><xml xmlns=\"https://developers.google.com/blockly/xml\"><block deletable=\"false\" type=\"advancement_trigger\" x=\"40\" y=\"80\"><next><block type=\"custom_trigger\" x=\"33\" y=\"63\"/></next></block></xml>"
  }
}