{
  "_fv": 66,
  "_type": "loottable",
  "definition": {
    "type": "Block",
    "pools": [
      {
        "minrolls": 1,
        "maxrolls": 1,
        "minbonusrolls": 1,
        "maxbonusrolls": 1,
        "hasbonusrolls": false,
        "entries": [
          {
            "type": "item",
            "item": {
              "value": "Blocks.AIR"
            },
            "weight": 78,
            "minCount": 1,
            "maxCount": 1,
            "minEnchantmentLevel": 0,
            "maxEnchantmentLevel": 0,
            "affectedByFortune": false,
            "explosionDecay": false,
            "silkTouchMode": 0
          },
          {
            "type": "item",
            "item": {
              "value": "CUSTOM:Kryptonite"
            },
            "weight": 12,
            "minCount": 1,
            "maxCount": 1,
            "minEnchantmentLevel": 0,
            "maxEnchantmentLevel": 0,
            "affectedByFortune": false,
            "explosionDecay": false,
            "silkTouchMode": 0
          },
          {
            "type": "item",
            "item": {
              "value": "CUSTOM:StrangeBone"
            },
            "weight": 16,
            "minCount": 1,
            "maxCount": 1,
            "minEnchantmentLevel": 0,
            "maxEnchantmentLevel": 0,
            "affectedByFortune": false,
            "explosionDecay": false,
            "silkTouchMode": 0
          },
          {
            "type": "item",
            "item": {
              "value": "CUSTOM:MicrochipTier3"
            },
            "weight": 2,
            "minCount": 1,
            "maxCount": 1,
            "minEnchantmentLevel": 0,
            "maxEnchantmentLevel": 0,
            "affectedByFortune": false,
            "explosionDecay": false,
            "silkTouchMode": 0
          },
          {
            "type": "item",
            "item": {
              "value": "CUSTOM:Microchip"
            },
            "weight": 16,
            "minCount": 1,
            "maxCount": 1,
            "minEnchantmentLevel": 0,
            "maxEnchantmentLevel": 0,
            "affectedByFortune": false,
            "explosionDecay": false,
            "silkTouchMode": 0
          },
          {
            "type": "item",
            "item": {
              "value": "CUSTOM:AdvancedCircuitBoard"
            },
            "weight": 8,
            "minCount": 1,
            "maxCount": 1,
            "minEnchantmentLevel": 0,
            "maxEnchantmentLevel": 0,
            "affectedByFortune": false,
            "explosionDecay": false,
            "silkTouchMode": 0
          },
          {
            "type": "item",
            "item": {
              "value": "CUSTOM:KryptoniteShard"
            },
            "weight": 26,
            "minCount": 2,
            "maxCount": 4,
            "minEnchantmentLevel": 0,
            "maxEnchantmentLevel": 0,
            "affectedByFortune": false,
            "explosionDecay": false,
            "silkTouchMode": 0
          },
          {
            "type": "item",
            "item": {
              "value": "CUSTOM:Raolite"
            },
            "weight": 52,
            "minCount": 1,
            "maxCount": 1,
            "minEnchantmentLevel": 0,
            "maxEnchantmentLevel": 0,
            "affectedByFortune": false,
            "explosionDecay": false,
            "silkTouchMode": 0
          },
          {
            "type": "item",
            "item": {
              "value": "CUSTOM:RawKryptium"
            },
            "weight": 1,
            "minCount": 1,
            "maxCount": 1,
            "minEnchantmentLevel": 0,
            "maxEnchantmentLevel": 0,
            "affectedByFortune": false,
            "explosionDecay": false,
            "silkTouchMode": 0
          }
        ]
      }
    ],
    "name": "blocks/meteorite_krypton_drops",
    "namespace": "mod"
  }
}